README.rst
setup.py
restframework_serializer_factory/__init__.py
restframework_serializer_factory/serializers.py
restframework_serializer_factory.egg-info/PKG-INFO
restframework_serializer_factory.egg-info/SOURCES.txt
restframework_serializer_factory.egg-info/dependency_links.txt
restframework_serializer_factory.egg-info/requires.txt
restframework_serializer_factory.egg-info/top_level.txt