Metadata-Version: 1.1
Name: restframework-serializer-factory
Version: 0.6.0
Summary: ('Factories for creating instances of restframework.serializers.ModelSerializer on demand.',)
Home-page: https://github.com/arpheno/django-rest-framework-serializer-factory/
Author: Sebastian Wozny
Author-email: sswozny@gmail.com
License: GPL
Keywords: django serializer factory rest framework
Platform: UNKNOWN
Classifier: Development Status :: 3 - Alpha
Classifier: Intended Audience :: Developers
Classifier: Framework :: Django
Classifier: Operating System :: POSIX :: Linux
Classifier: Programming Language :: Python
Classifier: Natural Language :: English
Classifier: License :: OSI Approved :: GNU General Public License v3 or later (GPLv3+)
Classifier: Topic :: Software Development :: Libraries
Requires: djangorestframework
